{
  "extends": "ktsn",
  "parser": "typescript-eslint-parser",
  "plugins": [
    "typescript"
  ],
  "rules": {
    "typescript/adjacent-overload-signatures": 2,
    "typescript/class-name-casing": 2,
    "typescript/no-array-constructor": 2,
    "typescript/no-empty-interface": 2,
    "typescript/no-triple-slash-reference": 2,
    "typescript/no-type-alias": [
      2,
      {
        "allowAliases": true,
        "allowCallbacks": true,
        "allowLiterals": "in-unions-and-intersections",
        "allowMappedTypes": true
      }
    ],
    "typescript/no-unused-vars": 2,
    "typescript/no-var-requires": 2,
    "typescript/type-annotation-spacing": 2
  }
}